zuper_html.pyi
zuper_html.cpython-310-aarch64-linux-gnu.so
zuper_html_z7-7.3.2202161758.dist-info/METADATA
zuper_html_z7-7.3.2202161758.dist-info/entry_points.txt
zuper_html_z7-7.3.2202161758.dist-info/WHEEL
zuper_html_z7-7.3.2202161758.dist-info/top_level.txt
zuper_html_z7-7.3.2202161758.dist-info/zip-safe
zuper_html_z7-7.3.2202161758.dist-info/RECORD
