Metadata-Version: 2.1
Name: zuper-html-z7
Version: 7.3.2202161758
Summary: UNKNOWN
Home-page: https://github.com/zupermind/zuper-html
Author: Andrea Censi
Author-email: info@zupermind.com
License: UNKNOWN
Platform: UNKNOWN
Requires-Dist: ansi2html
Requires-Dist: lxml
Requires-Dist: termcolor
Requires-Dist: typing-extensions
Requires-Dist: webcolors
Requires-Dist: zuper-commons-z7
Requires-Dist: zuper-typing-z7
Provides-Extra: test
Requires-Dist: nose ; extra == 'test'
